jpl_time/__init__.py
jpl_time/jpl_time.py
jpl_time/jpl_time_utilities/__init__.py
jpl_time/jpl_time_utilities/chronos_input_parsing.py
jpl_time/jpl_time_utilities/fetch_latest_kernels.py
jpl_time/jpl_time_utilities/time_globals.py
jpl_time/jpl_time_utilities/utility_functions.py
jpl_time-1.4.5.dist-info/LICENSE.txt
jpl_time-1.4.5.dist-info/METADATA
jpl_time-1.4.5.dist-info/WHEEL
jpl_time-1.4.5.dist-info/entry_points.txt
jpl_time-1.4.5.dist-info/top_level.txt
jpl_time-1.4.5.dist-info/RECORD
