Metadata-Version: 2.1
Name: jpl-time
Version: 1.4.5
Summary: Time and Duration classes which use SPICE to perform conversions and math.
Author: Flora Ridenhour
Author-email: Forrest.Ridenhour@jpl.nasa.gov
License: Apache License, Version 2.0
License-File: LICENSE.txt
Requires-Dist: nose
Requires-Dist: tornado
Requires-Dist: setuptools
Requires-Dist: six
Requires-Dist: certifi
Requires-Dist: pytz
Requires-Dist: wheel
Requires-Dist: numpy
Requires-Dist: spiceypy
